{
  "forge_marker": 1,
  "defaults": {
    "textures": {
      "side": "lazymystical:blocks/machine/side/3",
      "front": "lazymystical:blocks/machine/accelerant_fluid/3"
    },
    "model": "lazymystical:machine"
  },
  "variants": {
    "normal": [
      {}
    ],
    "facing": {
      "north": {
        "y": 0
      },
      "south": {
        "y": 180
      },
      "west": {
        "y": 270
      },
      "east": {
        "y": 90
      }
    },
    "inventory": {
      "transform": "forge:default-block"
    }
  }
}